[{
    "id": 0,
    "question": "You notice you can save funds by firing the school psychiatrist.",
    "leftText": "Cya!",
    "rightText": "But...",
    "onLeft": [20, -5, -5, -15],
    "onRight": [-5, 0, 5, 10],
    "requiredResponses": [],
    "requiredStats": [],
    "cardFamily": null,
    "image": "TeacherMan.png" 
  },
  {
    "id": 1,
    "question": "A teacher tells you that one her studens is acting very depressed and that a school should hire a new psychiatrist.",
    "leftText": "Anything for the kids!",
    "rightText": "Budget too low, sorry.",
    "onLeft": [25, 0, -5, -15],
    "onRight": [-20, 10, 10, 10],
    "requiredResponses": [{"cardId": 0, "swipedLeft": true}],
    "requiredStats": [],
    "cardFamily": null,
    "image": "StudentWoman.png"
  },
  {
    "id": 2,
    "question": "One of the students complaied the gym teacher is always yelling on all the students.",
    "leftText": "Enforce order",
    "rightText": "So?",
    "onLeft": [0, -5, -5, 5],
    "onRight": [0, 0, 5, -5],
    "requiredResponses": [],
    "requiredStats": [],
    "cardFamily": null,
    "image": "TeacherMan.png"
  },
  {
    "id": 3,
    "question": "Teacher got sick and there is no substitute.",
    "leftText": "Hire substitute teacher.",
    "rightText": "Give students self learning class.",
    "onLeft": [-5, 3, -5, -3],
    "onRight": [0, 0, -10, -5],
    "requiredResponses": [],
    "requiredStats": [],
    "cardFamily": null,
    "image": "TeacherMan.png"
  },
  {
    "id": 700,
    "question": "You notice one of the teachers isn't doing his job correctly, but the student body respects and adores him.",
    "leftText": "Fire the teacher.",
    "rightText": "Let him stay.",
    "onLeft": [0, -10, -15, -15],
    "onRight": [-5, 5, 10, 10],
    "requiredResponses": [],
    "requiredStats": [],
    "cardFamily": null
  },
  {
    "id": 993,
    "question": "One of the students complaied the gym teacher is always yelling on all the students.",
    "leftText": "Enforce order",
    "rightText": "So?",
    "onLeft": [0, -5, -5, 5],
    "onRight": [0, 0, 5, -5],
    "requiredResponses": [],
    "requiredStats": [],
    "cardFamily": null,
    "image": "TeacherMan.png"
  },
  {
    "id": 994,
    "question": "One of the students complaied the gym teacher is always yelling on all the students.",
    "leftText": "Enforce order",
    "rightText": "So?",
    "onLeft": [0, -5, -40, 5],
    "onRight": [0, 0, 5, -5],
    "requiredResponses": [],
    "requiredStats": [],
    "cardFamily": null,
    "image": "TeacherMan.png"
  },
  {
    "id": 995,
    "question": "One of the students complaied the gym teacher is always yelling on all the students.",
    "leftText": "Enforce order",
    "rightText": "So?",
    "onLeft": [0, -5, -5, 5],
    "onRight": [0, 0, 5, -5],
    "requiredResponses": [],
    "requiredStats": [],
    "cardFamily": null,
    "image": "TeacherMan.png"
  },
  {
    "id": 996,
    "question": "One of the students complaied the gym teacher is always yelling on all the students.",
    "leftText": "Enforce order",
    "rightText": "So?",
    "onLeft": [0, -5, -5, 5],
    "onRight": [0, 0, 5, -5],
    "requiredResponses": [],
    "requiredStats": [],
    "cardFamily": null,
    "image": "TeacherMan.png"
  },
  {
    "id": 997,
    "question": "One of the students complaied the gym teacher is always yelling on all the students.",
    "leftText": "Enforce order",
    "rightText": "So?",
    "onLeft": [0, -5, -5, 5],
    "onRight": [0, 0, 5, -5],
    "requiredResponses": [],
    "requiredStats": [],
    "cardFamily": null,
    "image": "TeacherMan.png"
  },
  {
    "id": 998,
    "question": "One of the students complaied the gym teacher is always yelling on all the students.",
    "leftText": "Enforce order",
    "rightText": "So?",
    "onLeft": [0, -5, -5, 5],
    "onRight": [0, 0, 5, -5],
    "requiredResponses": [],
    "requiredStats": [],
    "cardFamily": null,
    "image": "TeacherMan.png"
  },
  {
    "id": 999,
    "question": "One of the students complaied the gym teacher is always yelling on all the students.",
    "leftText": "Enforce order",
    "rightText": "So?",
    "onLeft": [0, -5, -5, 5],
    "onRight": [0, 0, 5, -5],
    "requiredResponses": [],
    "requiredStats": [],
    "cardFamily": null,
    "image": "TeacherMan.png"
  }
]
